CHANGES.txt
MANIFEST.in
README.rst
requirements.txt
setup.py
broadlink_auto_login.egg-info/PKG-INFO
broadlink_auto_login.egg-info/SOURCES.txt
broadlink_auto_login.egg-info/dependency_links.txt
broadlink_auto_login.egg-info/requires.txt
broadlink_auto_login.egg-info/top_level.txt
src/broadlink
src/broadlink_auto_login/__init__.py
src/broadlink_auto_login/__main__.py
src/broadlink_auto_login/_version.py
src/broadlink_auto_login/broadlink.py