Metadata-Version: 1.1
Name: broadlink-auto-login
Version: 0.1.0
Summary: Broadlink hotspot auto login script
Home-page: https://github.com/sandipbgt/broadlink-auto-login
Author: Sandip Bhagat
Author-email: sandipbgt@gmail.com
License: UNKNOWN
Platform: UNKNOWN
Classifier: Environment :: Console
Classifier: Programming Language :: Python :: 3
